shoppinglist/__init__.py
shoppinglist/cli.py
shoppinglist/items.py
shoppinglist/main.py
shoppinglist-1.0.0.data/scripts/shoppinglist
shoppinglist-1.0.0.dist-info/METADATA
shoppinglist-1.0.0.dist-info/RECORD
shoppinglist-1.0.0.dist-info/WHEEL
shoppinglist-1.0.0.dist-info/top_level.txt
shoppinglist-1.0.0.dist-info/zip-safe
