Metadata-Version: 2.1
Name: shoppinglist
Version: 1.0.0
Summary: Quickly different combinations of prices and spare money
Home-page: https://floriankempenich.github.io/Shopping-List
Author: Florian Kempenich
Author-email: Flori@nKempenich.com
License: MIT
Keywords: shopping calculator cost saving money shopping_list cli awesome
Platform: UNKNOWN
Classifier: Environment :: Console
Classifier: Intended Audience :: Developers
Classifier: Intended Audience :: End Users/Desktop
Classifier: License :: OSI Approved :: MIT License
Classifier: Topic :: Utilities
Classifier: Topic :: Office/Business :: Financial
Classifier: Topic :: Home Automation
Requires-Dist: click
